py_module_parser/__init__.py
py_module_parser/models.py
py_module_parser/parser.py
py_module_parser/utils.py
py_module_parser-0.5.0.dist-info/LICENSE
py_module_parser-0.5.0.dist-info/METADATA
py_module_parser-0.5.0.dist-info/WHEEL
py_module_parser-0.5.0.dist-info/RECORD
