Metadata-Version: 2.1
Name: py-module-parser
Version: 0.5.0
Summary: Python Module Parser is a library that parses Python modules and outputs information about imports, functions, variables, and their corresponding line numbers. This makes it easier to analyze and understand the structure of your Python code.
Home-page: https://github.com/xnuinside/py-module-parser
License: MIT
Author: Iuliia Volkova
Author-email: xnuinside@gmail.com
Requires-Python: >=3.8,<4.0
Classifier: License :: OSI Approved :: MIT License
Classifier: Programming Language :: Python :: 3
Classifier: Programming Language :: Python :: 3.8
Classifier: Programming Language :: Python :: 3.9
Classifier: Programming Language :: Python :: 3.10
Classifier: Programming Language :: Python :: 3.11
Classifier: Topic :: Software Development
Classifier: Topic :: Software Development :: Libraries
Classifier: Topic :: Software Development :: Libraries :: Python Modules
Classifier: Topic :: Utilities
Requires-Dist: pydantic (>=2.5.2,<3.0.0)
Project-URL: Repository, https://github.com/xnuinside/py-module-parser
